[
  {
    "link": "https://oeco.org.br/noticias/entenda-o-saldao-da-anp/",
    "titulo": "Entenda o “saldão da ANP”",
    "thumbnail": "https://oeco.org.br/wp-content/uploads/2022/04/Manifestantes-leiao.jpg",
    "resumo": "Perguntas e respostas sobre a oferta permanente de óleo e gás, que terá 379 blocos em licitação nesta quarta-feira (13)",
    "data_publicacao": "2022-04-13T21:39:00+00:00",
    "id": "e3063eb247dc9a69",
    "fonte": "Observatório do Clima (via (o)eco)",
    "site_id": "observatorio-do-clima",
    "grupo": "observatorio",
    "data_captura": "2026-07-11T21:38:43.024713+00:00"
  }
]
